fast_drf/__init__.py
fast_drf/core/__init__.py
fast_drf/core/api_generator.py
fast_drf/core/class_factory.py
fast_drf/core/serializer_generator.py
fast_drf/core/viewset_generator.py
fast_drf/mixins/__init__.py
fast_drf/mixins/expose_api_model_mixin.py
fast_drf/router.py
fast_drf/signals.py
fast_drf/tests/__init__.py
fast_drf/tests/base.py
fast_drf/tests/test_app/__init__.py
fast_drf/tests/test_app/apps.py
fast_drf/tests/test_app/migrations/0001_initial.py
fast_drf/tests/test_app/migrations/0002_userprofile_photo.py
fast_drf/tests/test_app/migrations/0003_post_photo.py
fast_drf/tests/test_app/migrations/__init__.py
fast_drf/tests/test_app/models.py
fast_drf/tests/test_app/receivers.py
fast_drf/tests/test_app/serializers.py
fast_drf/tests/test_app/urls.py
fast_drf/tests/test_app/views.py
fast_drf/tests/tests_serializer_generator.py
fast_drf/tests/tests_utility_methods.py
fast_drf/tests/tests_viewset_generator.py
fast_drf/utils/__init__.py
fast_drf/utils/enums.py
fast_drf/utils/parser.py
fast_drf/utils/predicate.py
fast_drf-2.2.12.dist-info/LICENSE
fast_drf-2.2.12.dist-info/METADATA
fast_drf-2.2.12.dist-info/WHEEL
fast_drf-2.2.12.dist-info/RECORD
