Metadata-Version: 2.1
Name: fast-drf
Version: 2.2.12
Summary: A simple model based API configarator written in Python and based of Django and Django REST Framework
License: MIT
Author: Mohammad Ashraful
Author-email: a5hraful@outlook.com
Requires-Python: >=3.8,<4.0
Classifier: License :: OSI Approved :: MIT License
Classifier: Programming Language :: Python :: 3
Classifier: Programming Language :: Python :: 3.8
Classifier: Programming Language :: Python :: 3.9
Classifier: Programming Language :: Python :: 3.10
Classifier: Programming Language :: Python :: 3.11
Requires-Dist: Django (>=2.0,<3.0)
Requires-Dist: djangorestframework (>=3.10,<4.0)
